<?xml version="1.0" encoding="utf-8"?>
<search>
  
  
  
  <entry>
    <title>HTML Tutorial</title>
    <link href="/2020/01/29/html%20%E6%95%99%E5%AD%A6/"/>
    <url>/2020/01/29/html%20%E6%95%99%E5%AD%A6/</url>
    
    <content type="html"><![CDATA[<h1 id="0-Introduction-to-HTML"><a href="#0-Introduction-to-HTML" class="headerlink" title="0 Introduction to HTML"></a>0 Introduction to HTML</h1><p>It is a kind of scripting language which can help coder to build website, although the website may not look beautiful, to be honest, all kinds of websites’ frame are built by html, according to above, you may have already knew the importance to learn html. And now let’s begin to learn it.</p><h1 id="1-1-Fundamental"><a href="#1-1-Fundamental" class="headerlink" title="1.1 Fundamental"></a>1.1 Fundamental</h1><p>Now, let’s code your first html program, just copy the code following.</p><figure class="highlight html"><table><tr><td class="gutter"><pre><span class="line">1</span><br><span class="line">2</span><br><span class="line">3</span><br><span class="line">4</span><br><span class="line">5</span><br><span class="line">6</span><br><span class="line">7</span><br><span class="line">8</span><br><span class="line">9</span><br><span class="line">10</span><br><span class="line">11</span><br></pre></td><td class="code"><pre><span class="line"><span class="meta">&lt;!DOCTYPE <span class="meta-keyword">html</span>&gt;</span></span><br><span class="line"><span class="tag">&lt;<span class="name">html</span>&gt;</span></span><br><span class="line"><span class="tag">&lt;<span class="name">head</span>&gt;</span></span><br><span class="line"><span class="tag">&lt;<span class="name">meta</span> <span class="attr">charset</span>=<span class="string">"utf=8"</span>&gt;</span></span><br><span class="line"><span class="tag">&lt;<span class="name">title</span>&gt;</span>PERELMAN LIAO<span class="tag">&lt;/<span class="name">title</span>&gt;</span></span><br><span class="line"><span class="tag">&lt;/<span class="name">head</span>&gt;</span></span><br><span class="line"><span class="tag">&lt;<span class="name">body</span>&gt;</span></span><br><span class="line">    <span class="tag">&lt;<span class="name">h1</span>&gt;</span>My first title<span class="tag">&lt;/<span class="name">h1</span>&gt;</span></span><br><span class="line">    <span class="tag">&lt;<span class="name">p</span>&gt;</span>My first paragraph<span class="tag">&lt;/<span class="name">p</span>&gt;</span></span><br><span class="line"><span class="tag">&lt;/<span class="name">body</span>&gt;</span></span><br><span class="line"><span class="tag">&lt;/<span class="name">html</span>&gt;</span></span><br></pre></td></tr></table></figure><p>After coding and runing, you may notice that before we code some html program we have to type the following code. </p><figure class="highlight html"><table><tr><td class="gutter"><pre><span class="line">1</span><br><span class="line">2</span><br><span class="line">3</span><br><span class="line">4</span><br><span class="line">5</span><br><span class="line">6</span><br><span class="line">7</span><br><span class="line">8</span><br><span class="line">9</span><br><span class="line">10</span><br></pre></td><td class="code"><pre><span class="line"><span class="meta">&lt;!DOCTYPE <span class="meta-keyword">html</span>&gt;</span></span><br><span class="line"><span class="tag">&lt;<span class="name">html</span>&gt;</span></span><br><span class="line"><span class="tag">&lt;<span class="name">head</span>&gt;</span></span><br><span class="line"><span class="tag">&lt;<span class="name">meta</span> <span class="attr">charset</span>=<span class="string">"utf=8"</span>&gt;</span></span><br><span class="line"><span class="tag">&lt;<span class="name">title</span>&gt;</span><span class="tag">&lt;/<span class="name">title</span>&gt;</span></span><br><span class="line"><span class="tag">&lt;/<span class="name">head</span>&gt;</span></span><br><span class="line"><span class="tag">&lt;<span class="name">body</span>&gt;</span></span><br><span class="line"></span><br><span class="line"><span class="tag">&lt;/<span class="name">body</span>&gt;</span></span><br><span class="line"><span class="tag">&lt;/<span class="name">html</span>&gt;</span></span><br></pre></td></tr></table></figure><p>And now let me explain the meaning to the code above.</p><figure class="highlight html"><table><tr><td class="gutter"><pre><span class="line">1</span><br></pre></td><td class="code"><pre><span class="line"><span class="meta">&lt;!DOCTYPE <span class="meta-keyword">html</span>&gt;</span></span><br></pre></td></tr></table></figure><p>This sentence is a kind of statement what uesed to be a long sring, and mainstream browsers that support the HTML 5 standard recognize this statement. So, you can regard it as an IOU, because use this language to do somthing that you want to do. All in all, you have to type this before you start coding.</p><figure class="highlight html"><table><tr><td class="gutter"><pre><span class="line">1</span><br><span class="line">2</span><br></pre></td><td class="code"><pre><span class="line"><span class="tag">&lt;<span class="name">html</span>&gt;</span></span><br><span class="line"><span class="tag">&lt;/<span class="name">html</span>&gt;</span></span><br></pre></td></tr></table></figure><p>This is a tag, you may notice that <html> means to start, and </html> means to stop. And by the way, you may find in the future that in html language, all the slash means to stop.</p><figure class="highlight html"><table><tr><td class="gutter"><pre><span class="line">1</span><br><span class="line">2</span><br></pre></td><td class="code"><pre><span class="line"><span class="tag">&lt;<span class="name">head</span>&gt;</span></span><br><span class="line"><span class="tag">&lt;/<span class="name">head</span>&gt;</span></span><br></pre></td></tr></table></figure><p>About this element (we will introduce this later), is also a kind of tag while means head tag, what’s more, this element is a container which contained all sorts of the head tag.</p><figure class="highlight html"><table><tr><td class="gutter"><pre><span class="line">1</span><br></pre></td><td class="code"><pre><span class="line"><span class="tag">&lt;<span class="name">meta</span> <span class="attr">charset</span>=<span class="string">"utf-8"</span>&gt;</span></span><br></pre></td></tr></table></figure><p>As for this, if you have some basis on programing, you may have already knew the “char”, “char” is a kind of variable which can storage some single-byte character type which means that “char” can storage every text since all kinds of language are formed with single-byte character. So, as we set the char as “utf-8” that means we can use both chinese and English in our website.</p><figure class="highlight html"><table><tr><td class="gutter"><pre><span class="line">1</span><br><span class="line">2</span><br><span class="line">3</span><br><span class="line">4</span><br><span class="line">5</span><br><span class="line">6</span><br><span class="line">7</span><br></pre></td><td class="code"><pre><span class="line"><span class="tag">&lt;<span class="name">title</span>&gt;</span></span><br><span class="line"><span class="tag">&lt;/<span class="name">title</span>&gt;</span></span><br><span class="line">```  </span><br><span class="line">The page title tag lets the viewer know what the current page is about, that is, what is the theme of the current page? So each website should have a separate title.</span><br><span class="line">```html</span><br><span class="line"><span class="tag">&lt;<span class="name">body</span>&gt;</span></span><br><span class="line"><span class="tag">&lt;/<span class="name">body</span>&gt;</span></span><br></pre></td></tr></table></figure><p>Seemingly, this is the place where you can write everything you want to write.</p><p>According to the explaination above, I believe you may have some basic knowledge about HTML.</p>]]></content>
    
    
    <categories>
      
      <category>Code</category>
      
    </categories>
    
    
    <tags>
      
      <tag>learning</tag>
      
      <tag>code</tag>
      
    </tags>
    
  </entry>
  
  
  
  <entry>
    <title>Single Variable Calculus(18.01)</title>
    <link href="/2020/01/27/calculus/"/>
    <url>/2020/01/27/calculus/</url>
    
    <content type="html"><![CDATA[<h2 id="Differentiation"><a href="#Differentiation" class="headerlink" title="Differentiation"></a><strong>Differentiation</strong></h2><h3 id="Two-main-problem"><a href="#Two-main-problem" class="headerlink" title="Two main problem"></a>Two main problem</h3><h4 id="A-what-is-a-derivative"><a href="#A-what-is-a-derivative" class="headerlink" title="A. what is a derivative?"></a>A. what is a derivative?</h4><h5 id="geometric-interp"><a href="#geometric-interp" class="headerlink" title="* geometric interp"></a>* geometric interp</h5><h5 id="physical-interp"><a href="#physical-interp" class="headerlink" title="* physical interp"></a>* physical interp</h5><h5 id="importance-of-all-measurements"><a href="#importance-of-all-measurements" class="headerlink" title="* importance of all measurements"></a>* importance of all measurements</h5><h4 id="B-how-to-differentiate"><a href="#B-how-to-differentiate" class="headerlink" title="B. how to differentiate?"></a>B. how to differentiate?</h4><h3 id="Geom-interp"><a href="#Geom-interp" class="headerlink" title="Geom interp"></a>Geom interp</h3><p>problem: find the tangent line to y=f(x) at P=(x<sub>0</sub>,y<sub>0</sub>)<br>y-y<sub>0</sub>=m(x-x<sub>0</sub>)<br><strong>point:</strong> y<sub>0</sub>=f(x<sub>0</sub>)<br><strong>slope:</strong> m=$\dot{f(x_0)}$<br><strong>DEF’N:</strong> $\dot{f(x)}$, the derivative of fat x<sub>0</sub>, is the slope of the tangent line to y=f(x) at P<br><strong><em>TANGENT LINE = LIMIT OF SECANT LINES PO AS Q –&gt; P</em></strong></p>]]></content>
    
    
    <categories>
      
      <category>Math</category>
      
    </categories>
    
    
    <tags>
      
      <tag>learning</tag>
      
      <tag>MIT ocw</tag>
      
    </tags>
    
  </entry>
  
  
  
  
</search>
